volume/__init__.py
volume/compression/README.md
volume/compression/__init__.py
volume/compression/volume.py
Volume-0.0.0.dist-info/LICENSE.md
Volume-0.0.0.dist-info/METADATA
Volume-0.0.0.dist-info/WHEEL
Volume-0.0.0.dist-info/top_level.txt
Volume-0.0.0.dist-info/RECORD
